dbc/__init__.py
dbc/LICENSE
dbc/__main__.py
dbc/README.md
dbc/dbc_linux_arm64.sig
dbc/dbc
dbc-0.2.0beta3.dist-info/licenses/LICENSE
dbc-0.2.0beta3.dist-info/entry_points.txt
dbc-0.2.0beta3.dist-info/METADATA
dbc-0.2.0beta3.dist-info/WHEEL
dbc-0.2.0beta3.dist-info/RECORD
