Metadata-Version: 2.4
Name: dbc
Version: 0.2.0beta3
Summary: dbc is a tool for installing ADBC drivers
License-Expression: Apache-2.0
License-File: LICENSE
Requires-Python: ~=3.5
Project-URL: homepage, https://columnar.tech/dbc
Project-URL: documentation, https://docs.columnar.tech/dbc/
Project-URL: tracker, https://github.com/columnar-tech/dbc/issues
Project-URL: source, https://github.com/columnar-tech/dbc
Classifier: Intended Audience :: Developers
Classifier: Topic :: Software Development
Classifier: Topic :: Scientific/Engineering
